uaioweb/__init__.py
micropython_uaioweb-0.0.3.dist-info/LICENSE
micropython_uaioweb-0.0.3.dist-info/METADATA
micropython_uaioweb-0.0.3.dist-info/WHEEL
micropython_uaioweb-0.0.3.dist-info/dependency_links.txt
micropython_uaioweb-0.0.3.dist-info/top_level.txt
micropython_uaioweb-0.0.3.dist-info/RECORD
