Metadata-Version: 2.1
Name: micropython-uaioweb
Version: 0.0.3
Summary: Minimal asyncio web server for HTTP and Websocket.
Home-page: https://github.com/damiencorpataux/micropython-uaioweb
Author: Davy Wybiral, Damien Corpataux (fork)
Author-email: not-disclosed@example.com, d@mien.ch
License: MIT
Keywords: micropython,python,web,server,http,websocket,asyncio,uasyncio,lightweight,simple,minimalistic
Classifier: Intended Audience :: Developers
Classifier: Environment :: Web Environment
Classifier: Programming Language :: Python
Classifier: Programming Language :: Python :: 3
Classifier: Programming Language :: Python :: Implementation :: MicroPython
Classifier: Topic :: Software Development :: Embedded Systems
Classifier: Topic :: Utilities
Classifier: Operating System :: OS Independent
Classifier: Natural Language :: English
Classifier: License :: OSI Approved :: MIT License
License-File: LICENSE
